denonavr/__init__.py
denonavr/api.py
denonavr/appcommand.py
denonavr/audyssey.py
denonavr/const.py
denonavr/decorators.py
denonavr/denonavr.py
denonavr/dirac.py
denonavr/exceptions.py
denonavr/foundation.py
denonavr/input.py
denonavr/soundmode.py
denonavr/ssdp.py
denonavr/tonecontrol.py
denonavr/volume.py
denonavr-1.1.2.dist-info/licenses/LICENSE
denonavr-1.1.2.dist-info/METADATA
denonavr-1.1.2.dist-info/WHEEL
denonavr-1.1.2.dist-info/top_level.txt
denonavr-1.1.2.dist-info/RECORD
