Metadata-Version: 2.4
Name: denonavr
Version: 1.1.2
Summary: Automation Library for Denon AVR receivers
Author-email: Oliver Goetz <scarface@mywoh.de>
License: MIT
Project-URL: Homepage, https://github.com/ol-iver/denonavr
Project-URL: Source, https://github.com/ol-iver/denonavr
Project-URL: Tracker, https://github.com/ol-iver/denonavr/issues
Platform: any
Classifier: Development Status :: 5 - Production/Stable
Classifier: Intended Audience :: Developers
Classifier: License :: OSI Approved :: MIT License
Classifier: Operating System :: OS Independent
Classifier: Topic :: Software Development :: Libraries
Classifier: Topic :: Home Automation
Classifier: Programming Language :: Python :: 3.8
Classifier: Programming Language :: Python :: 3.9
Classifier: Programming Language :: Python :: 3.10
Classifier: Programming Language :: Python :: 3.11
Classifier: Programming Language :: Python :: 3.12
Classifier: Programming Language :: Python :: 3.13
Requires-Python: >=3.8
License-File: LICENSE
Requires-Dist: asyncstdlib>=3.10.2
Requires-Dist: attrs>=21.2.0
Requires-Dist: defusedxml>=0.7.1
Requires-Dist: ftfy>=6.1.1
Requires-Dist: httpx>=0.23.1
Requires-Dist: netifaces>=0.11.0
Requires-Dist: async-timeout>=4.0.2; python_version < "3.11"
Provides-Extra: testing
Requires-Dist: pydocstyle; extra == "testing"
Requires-Dist: pylint; extra == "testing"
Requires-Dist: pytest; extra == "testing"
Requires-Dist: pytest-cov; extra == "testing"
Requires-Dist: pytest-timeout; extra == "testing"
Requires-Dist: pytest-asyncio; extra == "testing"
Requires-Dist: pytest-httpx; extra == "testing"
Requires-Dist: flake8-docstrings; extra == "testing"
Requires-Dist: flake8; extra == "testing"
Dynamic: license-file
